{
  "record_id": "PROV-5dd4d261-88a4-46dc-b6aa-6163e2abbb31",
  "session_id": "86fef3b4-4236-4ea9-a6bd-5bb824979be4",
  "timestamp": "2026-01-19T00:44:16.077073Z",
  "agent_id": "CrisisEngine",
  "activity_type": "simulation",
  "entity_context": {
    "inputs_hash": "-8886302881343950697",
    "inputs_sample": "{'scenario_id': 'FUT-002'}"
  },
  "outcome": {
    "status": "SUCCESS",
    "output_keys": [
      "scenario",
      "direct_impacts",
      "second_order_effects"
    ]
  },
  "metadata": {}
}