{
  "borrower_name": "Apple Inc.",
  "report_date": "2026-02-13T11:40:20.963415",
  "executive_summary": "The borrower Apple Inc. presents a mixed credit profile. Financial performance shows strong EBITDA ($132000.0M) but elevated leverage (2.2x).  [Ref: AAPL_10Q_FY25_Q1.pdf]",
  "sections": [
    {
      "title": "Executive Summary",
      "content": "The borrower Apple Inc. presents a mixed credit profile. Financial performance shows strong EBITDA ($132000.0M) but elevated leverage (2.2x).  [Ref: AAPL_10Q_FY25_Q1.pdf]",
      "citations": [
        {
          "doc_id": "AAPL_10Q_FY25_Q1.pdf",
          "chunk_id": "c7afd71e-c577-4094-8189-d06b1a0181fc",
          "page_number": 6
        }
      ],
      "author_agent": "Writer"
    },
    {
      "title": "Key Risks & Mitigants",
      "content": "Key Risks:\n- CONNECTED PARTY RISK: European Commission via Apple Inc. -> European Commission is High risk.\n- CONNECTED PARTY RISK: Google (Alphabet) via Apple Inc. -> Google (Alphabet) is High risk.\n",
      "citations": [],
      "author_agent": "Risk Officer"
    },
    {
      "title": "Financial Analysis",
      "content": "EBITDA: $132000.0M | Leverage: 2.2x",
      "citations": [],
      "author_agent": "Quant"
    }
  ],
  "key_strengths": [
    "Market leading position in core segment.",
    "Strong EBITDA generation ($132000.0M).",
    "Diversified customer base."
  ],
  "key_weaknesses": [
    "Elevated leverage at 2.2x.",
    "Exposure to cyclical end-markets.",
    "Recent management turnover."
  ],
  "mitigants": [
    "Strong free cash flow conversion.",
    "Demonstrated ability to deleverage.",
    "Sponsor support."
  ],
  "financial_ratios": {
    "leverage_ratio": 2.20530303030303,
    "dscr": 33.84615384615385,
    "current_ratio": 0.98,
    "revenue": 391000.0,
    "ebitda": 132000.0,
    "net_income": 102000.0
  },
  "historical_financials": [
    {
      "total_assets": 379300.0,
      "total_liabilities": 291100.0,
      "total_equity": 88200.0,
      "revenue": 391000.0,
      "ebitda": 132000.0,
      "net_income": 102000.0,
      "interest_expense": 3900.0,
      "dscr": 33.84615384615385,
      "leverage_ratio": 2.20530303030303,
      "current_ratio": 0.98,
      "period": "FY2025 Q1"
    },
    {
      "total_assets": 348956.0,
      "total_liabilities": 267812.0,
      "total_equity": 81144.0,
      "revenue": 351900.0,
      "ebitda": 116160.0,
      "net_income": 86700.0,
      "interest_expense": 3900.0,
      "dscr": 33.84615384615385,
      "leverage_ratio": 2.20530303030303,
      "current_ratio": 0.98,
      "period": "FY2024"
    },
    {
      "total_assets": 331508.2,
      "total_liabilities": 254421.4,
      "total_equity": 77086.8,
      "revenue": 323748.0,
      "ebitda": 104544.0,
      "net_income": 76296.0,
      "interest_expense": 3900.0,
      "dscr": 33.84615384615385,
      "leverage_ratio": 2.20530303030303,
      "current_ratio": 0.98,
      "period": "FY2023"
    }
  ],
  "dcf_analysis": {
    "free_cash_flow": [
      90090.0,
      93695.74499999998,
      96513.3312,
      98457.47345362497,
      99465.71557494001
    ],
    "growth_rate": 0.03,
    "wacc": 0.09,
    "terminal_value": 1707494.7840364703,
    "enterprise_value": 1480189.309036921,
    "equity_value": 1189089.309036921,
    "share_price": 185.0,
    "inputs": {
      "wacc": 0.09,
      "growth_rate": 0.03,
      "tax_rate_proxy": 0.35,
      "capex_margin": 0.05
    }
  },
  "pd_model": {
    "input_factors": {
      "Leverage Ratio": 2.20530303030303,
      "DSCR": 33.84615384615385,
      "Liquidity (Current Ratio)": 0.98,
      "EBITDA Margin": 0.3375959079283887
    },
    "model_score": 80.0,
    "implied_rating": "A",
    "one_year_pd": 0.001,
    "five_year_pd": 0.01
  },
  "lgd_analysis": {
    "seniority_structure": [
      {
        "tranche": "Revolving Credit Facility",
        "amount": 10000.0,
        "recovery_est": "90%"
      },
      {
        "tranche": "Senior Unsecured Notes (2030)",
        "amount": 2500.0,
        "recovery_est": "70%"
      },
      {
        "tranche": "Senior Unsecured Notes (2040)",
        "amount": 1500.0,
        "recovery_est": "60%"
      },
      {
        "tranche": "Term Loan A",
        "amount": 5000.0,
        "recovery_est": "80%"
      }
    ],
    "recovery_rate_assumption": 0.75,
    "loss_given_default": 0.25
  },
  "scenario_analysis": {
    "scenarios": [
      {
        "name": "Bear Case",
        "probability": 0.2,
        "revenue_growth": -0.05,
        "ebitda_margin": 0.2,
        "implied_share_price": 105.0
      },
      {
        "name": "Base Case",
        "probability": 0.5,
        "revenue_growth": 0.05,
        "ebitda_margin": 0.3,
        "implied_share_price": 150.0
      },
      {
        "name": "Bull Case",
        "probability": 0.3,
        "revenue_growth": 0.12,
        "ebitda_margin": 0.35,
        "implied_share_price": 210.0
      }
    ],
    "weighted_share_price": 159.0
  },
  "system_two_critique": {
    "critique_points": [
      "Credit thesis aligns with macro outlook.",
      "Valuation assumptions appear conservative."
    ],
    "conviction_score": 0.85,
    "verification_status": "PASS",
    "author_agent": "System 2"
  },
  "risk_score": 80.0,
  "credit_ratings": [
    {
      "agency": "Moody's",
      "rating": "Aaa",
      "outlook": "Stable",
      "date": "2026-02-13"
    },
    {
      "agency": "S&P",
      "rating": "AA+",
      "outlook": "Stable",
      "date": "2026-02-13"
    },
    {
      "agency": "Fitch",
      "rating": "AA+",
      "outlook": "Stable",
      "date": "2026-02-13"
    }
  ],
  "debt_facilities": [
    {
      "facility_type": "Revolving Credit Facility",
      "amount_committed": 10000.0,
      "amount_drawn": 0.0,
      "interest_rate": "SOFR + 0.75%",
      "maturity_date": "2028-09-15",
      "snc_rating": "Pass",
      "drc": 1.0,
      "ltv": 0.0,
      "conviction_score": 0.98,
      "lgd": 0.1,
      "recovery_rate": 0.9
    },
    {
      "facility_type": "Senior Unsecured Notes (2030)",
      "amount_committed": 2500.0,
      "amount_drawn": 2500.0,
      "interest_rate": "3.25%",
      "maturity_date": "2030-05-11",
      "snc_rating": "Pass",
      "drc": 1.0,
      "ltv": 0.1,
      "conviction_score": 0.95,
      "lgd": 0.3,
      "recovery_rate": 0.7
    },
    {
      "facility_type": "Senior Unsecured Notes (2040)",
      "amount_committed": 1500.0,
      "amount_drawn": 1500.0,
      "interest_rate": "4.10%",
      "maturity_date": "2040-02-28",
      "snc_rating": "Pass",
      "drc": 1.0,
      "ltv": 0.1,
      "conviction_score": 0.92,
      "lgd": 0.4,
      "recovery_rate": 0.6
    },
    {
      "facility_type": "Term Loan A",
      "amount_committed": 5000.0,
      "amount_drawn": 5000.0,
      "interest_rate": "SOFR + 1.10%",
      "maturity_date": "2027-03-30",
      "snc_rating": "Pass",
      "drc": 1.0,
      "ltv": 0.2,
      "conviction_score": 0.9,
      "lgd": 0.2,
      "recovery_rate": 0.8
    }
  ],
  "equity_data": {
    "market_cap": 3450000.0,
    "share_price": 225.5,
    "volume_avg_30d": 45000000.0,
    "pe_ratio": 31.5,
    "dividend_yield": 0.55,
    "beta": 1.15
  }
}